<?xml version="1.0" encoding="utf-8"?>
<!DOCTYPE hibernate-mapping PUBLIC "-//Hibernate/Hibernate Mapping DTD 3.0//EN"
"http://hibernate.sourceforge.net/hibernate-mapping-3.0.dtd">
<!-- Mapping file autogenerated by MyEclipse Persistence Tools -->
<hibernate-mapping>
	<class name="com.xinggang.project.entity.ClassT" table="ClassT"
		schema="dbo" catalog="Project_Data">
		<id name="classId" type="java.lang.Integer">
			<column name="ClassId" />
			<generator class="native" />
		</id>
		<many-to-one name="section" class="com.xinggang.project.entity.Section"
			fetch="select">
			<column name="ClassSectionId" />
		</many-to-one>
		<property name="className" type="java.lang.String">
			<column name="ClassName" length="50" />
		</property>
		<property name="classHuman" type="java.lang.String">
			<column name="ClassHuman" length="20" />
		</property>
		<property name="classDefinedOne" type="java.lang.String">
			<column name="ClassDefinedOne" length="50" />
		</property>
		<property name="classDefinedTwo" type="java.lang.String">
			<column name="ClassDefinedTwo" length="50" />
		</property>
		<property name="classRemark" type="java.lang.String">
			<column name="ClassRemark" />
		</property>
		<set name="interiorUsers" inverse="true">
			<key>
				<column name="IUserClassId" />
			</key>
			<one-to-many class="com.xinggang.project.entity.InteriorUser" />
		</set>

		<set name="working" inverse="true">
			<key>
				<column name="WorkingClassId" />
			</key>
			<one-to-many class="com.xinggang.project.entity.Working" />
		</set>
	</class>
</hibernate-mapping>
